{
    "CommitHash": "6f2e124d019b07b87a0b3fba0de431bdf90305a4",
    "ProjectName": "pytest-ansible",
    "AuthorID": "5ac7cd15",
    "AuthorDateFormat": "20171013",
    "AuthorTimeFormat": "132834",
    "Levels": {
        "After": {
            "A1": 382,
            "A2": 578,
            "B1": 90,
            "B2": 8,
            "C1": 10,
            "C2": 8
        },
        "Before": {
            "A1": 382,
            "A2": 578,
            "B1": 90,
            "B2": 8,
            "C1": 10,
            "C2": 8
        },
        "Difference": {
            "A1": 0,
            "A2": 0,
            "B1": 0,
            "B2": 0,
            "C1": 0,
            "C2": 0
        }
    }
}