{
    "CommitHash": "04fc312502ef5111424f2cb2fd58c941c8686fe9",
    "ProjectName": "indra",
    "AuthorID": "51f6ac85",
    "AuthorDateFormat": "20200618",
    "AuthorTimeFormat": "163341",
    "Levels": {
        "After": {
            "A1": 14,
            "A2": 18,
            "B1": 2,
            "B2": 0,
            "C1": 0,
            "C2": 0
        },
        "Before": {
            "A1": 0,
            "A2": 0,
            "B1": 0,
            "B2": 0,
            "C1": 0,
            "C2": 0
        },
        "Difference": {
            "A1": 14,
            "A2": 18,
            "B1": 2,
            "B2": 0,
            "C1": 0,
            "C2": 0
        }
    }
}