{
    "CommitHash": "0eede4ae7b38c9d15e15fa430c41ac0bd80d5d23",
    "ProjectName": "indra",
    "AuthorID": "c3d58abf",
    "AuthorDateFormat": "20200910",
    "AuthorTimeFormat": "171123",
    "Levels": {
        "After": {
            "A1": 4494,
            "A2": 3509,
            "B1": 265,
            "B2": 791,
            "C1": 68,
            "C2": 60
        },
        "Before": {
            "A1": 4494,
            "A2": 3509,
            "B1": 265,
            "B2": 791,
            "C1": 68,
            "C2": 60
        },
        "Difference": {
            "A1": 0,
            "A2": 0,
            "B1": 0,
            "B2": 0,
            "C1": 0,
            "C2": 0
        }
    }
}