{
    "CommitHash": "1ab2de43655f8cc0b6b2a8ac54cc03a1573b8efa",
    "ProjectName": "indra",
    "AuthorID": "c68ae1eb",
    "AuthorDateFormat": "20180404",
    "AuthorTimeFormat": "132052",
    "Levels": {
        "After": {
            "A1": 0,
            "A2": 0,
            "B1": 0,
            "B2": 0,
            "C1": 0,
            "C2": 0
        },
        "Before": {
            "A1": 130,
            "A2": 195,
            "B1": 1,
            "B2": 218,
            "C1": 0,
            "C2": 0
        },
        "Difference": {
            "A1": 0,
            "A2": 0,
            "B1": 0,
            "B2": 0,
            "C1": 0,
            "C2": 0
        }
    }
}