{
    "CommitHash": "3bfb383f00bdef242b4e432e6953d4f1de74cf27",
    "ProjectName": "indra",
    "AuthorID": "084d7872",
    "AuthorDateFormat": "20160519",
    "AuthorTimeFormat": "011830",
    "Levels": {
        "After": {
            "A1": 1,
            "A2": 3,
            "B1": 0,
            "B2": 0,
            "C1": 0,
            "C2": 0
        },
        "Before": {
            "A1": 1,
            "A2": 0,
            "B1": 0,
            "B2": 0,
            "C1": 0,
            "C2": 0
        },
        "Difference": {
            "A1": 0,
            "A2": 3,
            "B1": 0,
            "B2": 0,
            "C1": 0,
            "C2": 0
        }
    }
}