{
    "CommitHash": "4405788dab429bed17ba9aade7e65e574b68d657",
    "ProjectName": "indra",
    "AuthorID": "b57f55c0",
    "AuthorDateFormat": "20180808",
    "AuthorTimeFormat": "171550",
    "Levels": {
        "After": {
            "A1": 123,
            "A2": 130,
            "B1": 12,
            "B2": 4,
            "C1": 5,
            "C2": 1
        },
        "Before": {
            "A1": 119,
            "A2": 122,
            "B1": 11,
            "B2": 4,
            "C1": 5,
            "C2": 1
        },
        "Difference": {
            "A1": 4,
            "A2": 8,
            "B1": 1,
            "B2": 0,
            "C1": 0,
            "C2": 0
        }
    }
}