{
    "CommitHash": "51047893934f925fedae22581ffaac06c0a41745",
    "ProjectName": "indra",
    "AuthorID": "084d7872",
    "AuthorDateFormat": "20200514",
    "AuthorTimeFormat": "015545",
    "Levels": {
        "After": {
            "A1": 0,
            "A2": 0,
            "B1": 0,
            "B2": 0,
            "C1": 0,
            "C2": 0
        },
        "Before": {
            "A1": 257,
            "A2": 235,
            "B1": 19,
            "B2": 1,
            "C1": 12,
            "C2": 2
        },
        "Difference": {
            "A1": 0,
            "A2": 0,
            "B1": 0,
            "B2": 0,
            "C1": 0,
            "C2": 0
        }
    }
}