{
    "CommitHash": "5c716f2c75979a4711c78fe5c334e9abdd96c592",
    "ProjectName": "indra",
    "AuthorID": "c3d58abf",
    "AuthorDateFormat": "20201013",
    "AuthorTimeFormat": "101121",
    "Levels": {
        "After": {
            "A1": 495,
            "A2": 238,
            "B1": 75,
            "B2": 0,
            "C1": 31,
            "C2": 8
        },
        "Before": {
            "A1": 495,
            "A2": 238,
            "B1": 75,
            "B2": 0,
            "C1": 31,
            "C2": 8
        },
        "Difference": {
            "A1": 0,
            "A2": 0,
            "B1": 0,
            "B2": 0,
            "C1": 0,
            "C2": 0
        }
    }
}