{
    "CommitHash": "63e38c1f0e04338e0115fdb0771e9e6896ad6a85",
    "ProjectName": "indra",
    "AuthorID": "084d7872",
    "AuthorDateFormat": "20161021",
    "AuthorTimeFormat": "095420",
    "Levels": {
        "After": {
            "A1": 41,
            "A2": 59,
            "B1": 4,
            "B2": 1,
            "C1": 0,
            "C2": 0
        },
        "Before": {
            "A1": 33,
            "A2": 54,
            "B1": 2,
            "B2": 1,
            "C1": 0,
            "C2": 0
        },
        "Difference": {
            "A1": 8,
            "A2": 5,
            "B1": 2,
            "B2": 0,
            "C1": 0,
            "C2": 0
        }
    }
}