{
    "CommitHash": "653b7c9f091039583ddac0e5dec537bcef6aaca7",
    "ProjectName": "indra",
    "AuthorID": "b57f55c0",
    "AuthorDateFormat": "20190306",
    "AuthorTimeFormat": "113105",
    "Levels": {
        "After": {
            "A1": 166,
            "A2": 92,
            "B1": 12,
            "B2": 0,
            "C1": 5,
            "C2": 1
        },
        "Before": {
            "A1": 167,
            "A2": 92,
            "B1": 12,
            "B2": 0,
            "C1": 5,
            "C2": 1
        },
        "Difference": {
            "A1": 0,
            "A2": 0,
            "B1": 0,
            "B2": 0,
            "C1": 0,
            "C2": 0
        }
    }
}