{
    "CommitHash": "96c4c47f07895521fe5ad705e8cb693869a8e6c2",
    "ProjectName": "indra",
    "AuthorID": "ebe0e386",
    "AuthorDateFormat": "20150209",
    "AuthorTimeFormat": "210922",
    "Levels": {
        "After": {
            "A1": 19,
            "A2": 72,
            "B1": 2,
            "B2": 0,
            "C1": 1,
            "C2": 0
        },
        "Before": {
            "A1": 8,
            "A2": 20,
            "B1": 2,
            "B2": 0,
            "C1": 1,
            "C2": 0
        },
        "Difference": {
            "A1": 11,
            "A2": 52,
            "B1": 0,
            "B2": 0,
            "C1": 0,
            "C2": 0
        }
    }
}