{
    "CommitHash": "980a68e0efc9c3a2c6486b39608c0f98b11901c7",
    "ProjectName": "indra",
    "AuthorID": "73b40ddc",
    "AuthorDateFormat": "20210318",
    "AuthorTimeFormat": "163403",
    "Levels": {
        "After": {
            "A1": 23,
            "A2": 14,
            "B1": 2,
            "B2": 0,
            "C1": 3,
            "C2": 1
        },
        "Before": {
            "A1": 0,
            "A2": 0,
            "B1": 0,
            "B2": 0,
            "C1": 0,
            "C2": 0
        },
        "Difference": {
            "A1": 23,
            "A2": 14,
            "B1": 2,
            "B2": 0,
            "C1": 3,
            "C2": 1
        }
    }
}