{
    "CommitHash": "a557617be88e8345893d575e56ec8aed92b88c61",
    "ProjectName": "indra",
    "AuthorID": "c68ae1eb",
    "AuthorDateFormat": "20170725",
    "AuthorTimeFormat": "191014",
    "Levels": {
        "After": {
            "A1": 269,
            "A2": 162,
            "B1": 13,
            "B2": 29,
            "C1": 4,
            "C2": 0
        },
        "Before": {
            "A1": 264,
            "A2": 157,
            "B1": 13,
            "B2": 29,
            "C1": 4,
            "C2": 0
        },
        "Difference": {
            "A1": 5,
            "A2": 5,
            "B1": 0,
            "B2": 0,
            "C1": 0,
            "C2": 0
        }
    }
}