{
    "CommitHash": "a81b32b246b8ce406306399267bd28744b96187e",
    "ProjectName": "indra",
    "AuthorID": "084d7872",
    "AuthorDateFormat": "20200726",
    "AuthorTimeFormat": "145702",
    "Levels": {
        "After": {
            "A1": 25,
            "A2": 21,
            "B1": 0,
            "B2": 21,
            "C1": 0,
            "C2": 0
        },
        "Before": {
            "A1": 24,
            "A2": 21,
            "B1": 0,
            "B2": 21,
            "C1": 0,
            "C2": 0
        },
        "Difference": {
            "A1": 1,
            "A2": 0,
            "B1": 0,
            "B2": 0,
            "C1": 0,
            "C2": 0
        }
    }
}