{
    "CommitHash": "a8541c65416b809fefa5aa2451a821972474ea7c",
    "ProjectName": "indra",
    "AuthorID": "1e31d299",
    "AuthorDateFormat": "20160512",
    "AuthorTimeFormat": "175600",
    "Levels": {
        "After": {
            "A1": 39,
            "A2": 27,
            "B1": 3,
            "B2": 0,
            "C1": 0,
            "C2": 0
        },
        "Before": {
            "A1": 0,
            "A2": 0,
            "B1": 0,
            "B2": 0,
            "C1": 0,
            "C2": 0
        },
        "Difference": {
            "A1": 39,
            "A2": 27,
            "B1": 3,
            "B2": 0,
            "C1": 0,
            "C2": 0
        }
    }
}