{
    "CommitHash": "aab7e479360cbbe43da1a614b7efacac6b2a152d",
    "ProjectName": "indra",
    "AuthorID": "1038d6e9",
    "AuthorDateFormat": "20200914",
    "AuthorTimeFormat": "182534",
    "Levels": {
        "After": {
            "A1": 270,
            "A2": 101,
            "B1": 47,
            "B2": 0,
            "C1": 21,
            "C2": 2
        },
        "Before": {
            "A1": 270,
            "A2": 101,
            "B1": 47,
            "B2": 0,
            "C1": 21,
            "C2": 2
        },
        "Difference": {
            "A1": 0,
            "A2": 0,
            "B1": 0,
            "B2": 0,
            "C1": 0,
            "C2": 0
        }
    }
}