{
    "CommitHash": "c5cd3ade652b8fe4ff5824067841b487af5ebb59",
    "ProjectName": "indra",
    "AuthorID": "b57f55c0",
    "AuthorDateFormat": "20180510",
    "AuthorTimeFormat": "142008",
    "Levels": {
        "After": {
            "A1": 35,
            "A2": 24,
            "B1": 5,
            "B2": 0,
            "C1": 2,
            "C2": 1
        },
        "Before": {
            "A1": 35,
            "A2": 24,
            "B1": 5,
            "B2": 0,
            "C1": 2,
            "C2": 1
        },
        "Difference": {
            "A1": 0,
            "A2": 0,
            "B1": 0,
            "B2": 0,
            "C1": 0,
            "C2": 0
        }
    }
}