{
    "CommitHash": "d179d9a184a9ee472cea80100ec8b6ca72a6b5b8",
    "ProjectName": "indra",
    "AuthorID": "c3d58abf",
    "AuthorDateFormat": "20210310",
    "AuthorTimeFormat": "171616",
    "Levels": {
        "After": {
            "A1": 0,
            "A2": 0,
            "B1": 1,
            "B2": 0,
            "C1": 0,
            "C2": 0
        },
        "Before": {
            "A1": 0,
            "A2": 0,
            "B1": 1,
            "B2": 0,
            "C1": 0,
            "C2": 0
        },
        "Difference": {
            "A1": 0,
            "A2": 0,
            "B1": 0,
            "B2": 0,
            "C1": 0,
            "C2": 0
        }
    }
}