{
    "CommitHash": "d47988735be7fd8ebb7ce1ead68e5ef895b45640",
    "ProjectName": "indra",
    "AuthorID": "a639f5bc",
    "AuthorDateFormat": "20210706",
    "AuthorTimeFormat": "172641",
    "Levels": {
        "After": {
            "A1": 44,
            "A2": 31,
            "B1": 5,
            "B2": 1,
            "C1": 0,
            "C2": 0
        },
        "Before": {
            "A1": 44,
            "A2": 31,
            "B1": 5,
            "B2": 1,
            "C1": 0,
            "C2": 0
        },
        "Difference": {
            "A1": 0,
            "A2": 0,
            "B1": 0,
            "B2": 0,
            "C1": 0,
            "C2": 0
        }
    }
}