{
    "CommitHash": "f36be8cf9b9dd6ccf98eb16bb4aa52a4a017d11a",
    "ProjectName": "indra",
    "AuthorID": "084d7872",
    "AuthorDateFormat": "20180519",
    "AuthorTimeFormat": "170036",
    "Levels": {
        "After": {
            "A1": 0,
            "A2": 0,
            "B1": 1,
            "B2": 0,
            "C1": 0,
            "C2": 0
        },
        "Before": {
            "A1": 0,
            "A2": 0,
            "B1": 1,
            "B2": 0,
            "C1": 0,
            "C2": 0
        },
        "Difference": {
            "A1": 0,
            "A2": 0,
            "B1": 0,
            "B2": 0,
            "C1": 0,
            "C2": 0
        }
    }
}