{
    "CommitHash": "f591dced9675c5337e88d5871e65a82d185c96d0",
    "ProjectName": "indra",
    "AuthorID": "b57f55c0",
    "AuthorDateFormat": "20171106",
    "AuthorTimeFormat": "162036",
    "Levels": {
        "After": {
            "A1": 250,
            "A2": 238,
            "B1": 39,
            "B2": 2,
            "C1": 13,
            "C2": 4
        },
        "Before": {
            "A1": 250,
            "A2": 238,
            "B1": 39,
            "B2": 2,
            "C1": 13,
            "C2": 4
        },
        "Difference": {
            "A1": 0,
            "A2": 0,
            "B1": 0,
            "B2": 0,
            "C1": 0,
            "C2": 0
        }
    }
}