{
    "CommitHash": "f9d46e8cb9f9f19356dd71eef5cf02800b3ed8b9",
    "ProjectName": "indra",
    "AuthorID": "b57f55c0",
    "AuthorDateFormat": "20181030",
    "AuthorTimeFormat": "142513",
    "Levels": {
        "After": {
            "A1": 1712,
            "A2": 1504,
            "B1": 175,
            "B2": 23,
            "C1": 45,
            "C2": 56
        },
        "Before": {
            "A1": 1712,
            "A2": 1504,
            "B1": 175,
            "B2": 23,
            "C1": 45,
            "C2": 56
        },
        "Difference": {
            "A1": 0,
            "A2": 0,
            "B1": 0,
            "B2": 0,
            "C1": 0,
            "C2": 0
        }
    }
}