{
    "CommitHash": "4ba8b41dd5b0ff9e90f2631c8dda0d0af06dc8a0",
    "ProjectName": "pygeometa",
    "AuthorID": "37a3ec9d",
    "AuthorDateFormat": "20220228",
    "AuthorTimeFormat": "201259",
    "Levels": {
        "After": {
            "A1": 84,
            "A2": 54,
            "B1": 11,
            "B2": 2,
            "C1": 2,
            "C2": 1
        },
        "Before": {
            "A1": 84,
            "A2": 54,
            "B1": 11,
            "B2": 2,
            "C1": 2,
            "C2": 1
        },
        "Difference": {
            "A1": 0,
            "A2": 0,
            "B1": 0,
            "B2": 0,
            "C1": 0,
            "C2": 0
        }
    }
}