{
    "CommitHash": "2f87211eaf4ed7a5803e3005aef1763957d3236a",
    "ProjectName": "alicat",
    "AuthorID": "4836c036",
    "AuthorDateFormat": "20230703",
    "AuthorTimeFormat": "225838",
    "Levels": {
        "After": {
            "A1": 7,
            "A2": 4,
            "B1": 4,
            "B2": 0,
            "C1": 0,
            "C2": 0
        },
        "Before": {
            "A1": 7,
            "A2": 4,
            "B1": 4,
            "B2": 0,
            "C1": 0,
            "C2": 0
        },
        "Difference": {
            "A1": 0,
            "A2": 0,
            "B1": 0,
            "B2": 0,
            "C1": 0,
            "C2": 0
        }
    }
}