{
    "CommitHash": "7f05272e0164e882fea8fd05fee5d555b23f8014",
    "ProjectName": "cloudmesh-common",
    "AuthorID": "84032fb5",
    "AuthorDateFormat": "20220123",
    "AuthorTimeFormat": "192714",
    "Levels": {
        "After": {
            "A1": 2,
            "A2": 16,
            "B1": 0,
            "B2": 0,
            "C1": 0,
            "C2": 0
        },
        "Before": {
            "A1": 2,
            "A2": 16,
            "B1": 0,
            "B2": 0,
            "C1": 0,
            "C2": 0
        },
        "Difference": {
            "A1": 0,
            "A2": 0,
            "B1": 0,
            "B2": 0,
            "C1": 0,
            "C2": 0
        }
    }
}