{
    "CommitHash": "bd92a73298bd8fa57e09da97803d3f61b2ed26d8",
    "ProjectName": "aorun",
    "AuthorID": "75756218",
    "AuthorDateFormat": "20170314",
    "AuthorTimeFormat": "015827",
    "Levels": {
        "After": {
            "A1": 69,
            "A2": 109,
            "B1": 7,
            "B2": 0,
            "C1": 0,
            "C2": 2
        },
        "Before": {
            "A1": 51,
            "A2": 74,
            "B1": 7,
            "B2": 0,
            "C1": 0,
            "C2": 2
        },
        "Difference": {
            "A1": 18,
            "A2": 35,
            "B1": 0,
            "B2": 0,
            "C1": 0,
            "C2": 0
        }
    }
}