{
    "CommitHash": "57dcce7ed9a170c42752b6aa5092224cb67a4168",
    "ProjectName": "django-distill",
    "AuthorID": "f19c5535",
    "AuthorDateFormat": "20150426",
    "AuthorTimeFormat": "110229",
    "Levels": {
        "After": {
            "A1": 22,
            "A2": 65,
            "B1": 7,
            "B2": 0,
            "C1": 0,
            "C2": 0
        },
        "Before": {
            "A1": 22,
            "A2": 52,
            "B1": 7,
            "B2": 0,
            "C1": 0,
            "C2": 0
        },
        "Difference": {
            "A1": 0,
            "A2": 13,
            "B1": 0,
            "B2": 0,
            "C1": 0,
            "C2": 0
        }
    }
}