{
    "CommitHash": "8a6c6774971ca89a27be6639ec028530e02f24df",
    "ProjectName": "django-distill",
    "AuthorID": "8eba2d11",
    "AuthorDateFormat": "20170925",
    "AuthorTimeFormat": "173239",
    "Levels": {
        "After": {
            "A1": 107,
            "A2": 93,
            "B1": 16,
            "B2": 0,
            "C1": 4,
            "C2": 0
        },
        "Before": {
            "A1": 103,
            "A2": 91,
            "B1": 15,
            "B2": 0,
            "C1": 3,
            "C2": 0
        },
        "Difference": {
            "A1": 4,
            "A2": 2,
            "B1": 1,
            "B2": 0,
            "C1": 1,
            "C2": 0
        }
    }
}