{
    "CommitHash": "0f69aa9e6f51555ee2ecc098d7478ac971258b43",
    "ProjectName": "batchflow",
    "AuthorID": "5ed22c7a",
    "AuthorDateFormat": "20170602",
    "AuthorTimeFormat": "102622",
    "Levels": {
        "After": {
            "A1": 150,
            "A2": 143,
            "B1": 34,
            "B2": 1,
            "C1": 6,
            "C2": 1
        },
        "Before": {
            "A1": 156,
            "A2": 143,
            "B1": 33,
            "B2": 1,
            "C1": 6,
            "C2": 1
        },
        "Difference": {
            "A1": 0,
            "A2": 0,
            "B1": 1,
            "B2": 0,
            "C1": 0,
            "C2": 0
        }
    }
}