{
    "CommitHash": "19edad5d072583c70d2aa71d217ad5263c208e4c",
    "ProjectName": "batchflow",
    "AuthorID": "16e91cdd",
    "AuthorDateFormat": "20180423",
    "AuthorTimeFormat": "172510",
    "Levels": {
        "After": {
            "A1": 72,
            "A2": 50,
            "B1": 20,
            "B2": 0,
            "C1": 0,
            "C2": 3
        },
        "Before": {
            "A1": 74,
            "A2": 50,
            "B1": 20,
            "B2": 0,
            "C1": 0,
            "C2": 3
        },
        "Difference": {
            "A1": 0,
            "A2": 0,
            "B1": 0,
            "B2": 0,
            "C1": 0,
            "C2": 0
        }
    }
}