{
    "CommitHash": "70bc069b5ae6516951b1792bf9cbbc64ff864138",
    "ProjectName": "batchflow",
    "AuthorID": "f4c7a320",
    "AuthorDateFormat": "20221118",
    "AuthorTimeFormat": "111937",
    "Levels": {
        "After": {
            "A1": 127,
            "A2": 61,
            "B1": 39,
            "B2": 0,
            "C1": 5,
            "C2": 9
        },
        "Before": {
            "A1": 127,
            "A2": 61,
            "B1": 39,
            "B2": 0,
            "C1": 5,
            "C2": 9
        },
        "Difference": {
            "A1": 0,
            "A2": 0,
            "B1": 0,
            "B2": 0,
            "C1": 0,
            "C2": 0
        }
    }
}