{
    "CommitHash": "e441769fcc6dda9365ab09a47c60dfa9533a03da",
    "ProjectName": "batchflow",
    "AuthorID": "16bb6856",
    "AuthorDateFormat": "20191031",
    "AuthorTimeFormat": "152447",
    "Levels": {
        "After": {
            "A1": 516,
            "A2": 474,
            "B1": 96,
            "B2": 2,
            "C1": 6,
            "C2": 1
        },
        "Before": {
            "A1": 519,
            "A2": 476,
            "B1": 96,
            "B2": 2,
            "C1": 6,
            "C2": 1
        },
        "Difference": {
            "A1": 0,
            "A2": 0,
            "B1": 0,
            "B2": 0,
            "C1": 0,
            "C2": 0
        }
    }
}