{
    "CommitHash": "fac04b8ac4b6dd26734c11584e33acffd0117ea3",
    "ProjectName": "batchflow",
    "AuthorID": "9537a695",
    "AuthorDateFormat": "20191016",
    "AuthorTimeFormat": "134303",
    "Levels": {
        "After": {
            "A1": 17,
            "A2": 16,
            "B1": 2,
            "B2": 0,
            "C1": 0,
            "C2": 0
        },
        "Before": {
            "A1": 17,
            "A2": 16,
            "B1": 2,
            "B2": 0,
            "C1": 0,
            "C2": 0
        },
        "Difference": {
            "A1": 0,
            "A2": 0,
            "B1": 0,
            "B2": 0,
            "C1": 0,
            "C2": 0
        }
    }
}