{
    "CommitHash": "4ab47b873225f8b1d11797024dd3f3c50c00a0c8",
    "ProjectName": "pandas-profiling",
    "AuthorID": "c0b783e5",
    "AuthorDateFormat": "20200925",
    "AuthorTimeFormat": "172231",
    "Levels": {
        "After": {
            "A1": 73,
            "A2": 112,
            "B1": 8,
            "B2": 0,
            "C1": 0,
            "C2": 2
        },
        "Before": {
            "A1": 74,
            "A2": 114,
            "B1": 8,
            "B2": 0,
            "C1": 0,
            "C2": 2
        },
        "Difference": {
            "A1": 0,
            "A2": 0,
            "B1": 0,
            "B2": 0,
            "C1": 0,
            "C2": 0
        }
    }
}