{
    "CommitHash": "f0846086da42411dbb2ca581df1520c6590cb4a5",
    "ProjectName": "pandas-profiling",
    "AuthorID": "e45df0e7",
    "AuthorDateFormat": "20220831",
    "AuthorTimeFormat": "124732",
    "Levels": {
        "After": {
            "A1": 344,
            "A2": 506,
            "B1": 36,
            "B2": 11,
            "C1": 10,
            "C2": 4
        },
        "Before": {
            "A1": 344,
            "A2": 506,
            "B1": 36,
            "B2": 11,
            "C1": 10,
            "C2": 4
        },
        "Difference": {
            "A1": 0,
            "A2": 0,
            "B1": 0,
            "B2": 0,
            "C1": 0,
            "C2": 0
        }
    }
}