{
    "CommitHash": "080e53b88cb3899ee17434d51546c21ef4268312",
    "ProjectName": "pyngrok",
    "AuthorID": "19b6335a",
    "AuthorDateFormat": "20221126",
    "AuthorTimeFormat": "132717",
    "Levels": {
        "After": {
            "A1": 668,
            "A2": 1877,
            "B1": 102,
            "B2": 2,
            "C1": 3,
            "C2": 0
        },
        "Before": {
            "A1": 619,
            "A2": 1652,
            "B1": 96,
            "B2": 2,
            "C1": 3,
            "C2": 0
        },
        "Difference": {
            "A1": 49,
            "A2": 225,
            "B1": 6,
            "B2": 0,
            "C1": 0,
            "C2": 0
        }
    }
}