{
    "CommitHash": "22ff819d0ab6e3adfed59579a2f33a53b3c22356",
    "ProjectName": "pyngrok",
    "AuthorID": "19b6335a",
    "AuthorDateFormat": "20221126",
    "AuthorTimeFormat": "185818",
    "Levels": {
        "After": {
            "A1": 472,
            "A2": 1575,
            "B1": 73,
            "B2": 2,
            "C1": 1,
            "C2": 0
        },
        "Before": {
            "A1": 460,
            "A2": 1559,
            "B1": 75,
            "B2": 2,
            "C1": 1,
            "C2": 0
        },
        "Difference": {
            "A1": 12,
            "A2": 16,
            "B1": 0,
            "B2": 0,
            "C1": 0,
            "C2": 0
        }
    }
}