{
    "CommitHash": "b763d39c5b6906d7703c0502c6dc040838f44232",
    "ProjectName": "pyngrok",
    "AuthorID": "cc92f212",
    "AuthorDateFormat": "20181217",
    "AuthorTimeFormat": "151118",
    "Levels": {
        "After": {
            "A1": 145,
            "A2": 280,
            "B1": 36,
            "B2": 0,
            "C1": 1,
            "C2": 0
        },
        "Before": {
            "A1": 128,
            "A2": 246,
            "B1": 34,
            "B2": 0,
            "C1": 1,
            "C2": 0
        },
        "Difference": {
            "A1": 17,
            "A2": 34,
            "B1": 2,
            "B2": 0,
            "C1": 0,
            "C2": 0
        }
    }
}